README.txt
setup.py
date_calculate/__init__.py
date_calculate/date_calculate.py
date_calculate.egg-info/PKG-INFO
date_calculate.egg-info/SOURCES.txt
date_calculate.egg-info/dependency_links.txt
date_calculate.egg-info/top_level.txt
date_calculate.egg-info/zip-safe