Metadata-Version: 1.1
Name: date-calculate
Version: 1.0.1
Summary: calculate how many years,months,weeks,days between the start date and end date.
Home-page: http://blog.useasp.net/
Author: Zhang Lin
Author-email: luoyelin1989@126.com
License: MIT
Keywords: date interval
Platform: UNKNOWN
Classifier: License :: OSI Approved :: MIT License
Classifier: Programming Language :: Python
Classifier: Intended Audience :: Developers
Classifier: Operating System :: OS Independent
